mautrix_wechat/__init__.py
mautrix_wechat/__main__.py
mautrix_wechat/commands/__init__.py
mautrix_wechat/commands/test.py
mautrix_wechat/commands/types.py
mautrix_wechat/config.py
mautrix_wechat/db/__init__.py
mautrix_wechat/db/message.py
mautrix_wechat/db/portal.py
mautrix_wechat/db/puppet.py
mautrix_wechat/db/upgrade.py
mautrix_wechat/db/user.py
mautrix_wechat/example-config.yaml
mautrix_wechat/formatter/__init__.py
mautrix_wechat/formatter/from_matrix.py
mautrix_wechat/formatter/from_wechat.py
mautrix_wechat/matrix.py
mautrix_wechat/portal.py
mautrix_wechat/puppet.py
mautrix_wechat/user.py
mautrix_wechat/util/__init__.py
mautrix_wechat/util/color_log.py
mautrix_wechat/util/containers.py
mautrix_wechat/util/file.py
mautrix_wechat/util/locks.py
mautrix_wechat/version.py
mautrix_wechat/wechat.py
wesdk/README.md
wesdk/__init__.py
wesdk/client.py
wesdk/image.py
wesdk/query.py
wesdk/test.py
wesdk/types.py
mautrix_wechat/__version__.py
mautrix_wechat-0.0.1.dist-info/WHEEL
mautrix_wechat-0.0.1.dist-info/METADATA
mautrix_wechat-0.0.1.dist-info/license_files/LICENSE
mautrix_wechat-0.0.1.dist-info/RECORD
