Metadata-Version: 2.1
Name: mautrix-wechat
Version: 0.0.1
Summary: A Matrix-Wechat puppeting bridge, based on https://github.com/ChisBread/wechat-box
License: MIT
Author-email: Lei Shi <me@leishi.io>
Requires-Python: >=3.8
Requires-Dist: aiohttp>=3,<4
Requires-Dist: asyncpg>=0.25
Requires-Dist: attrs>=19.1
Requires-Dist: commonmark>=0.8,<0.10
Requires-Dist: lxml>=4.9.1
Requires-Dist: mautrix>=0.16.0
Requires-Dist: python-dateutil
Requires-Dist: python-magic>=0.4.27
Requires-Dist: ruamel.yaml>=0.15.94,<0.18
Requires-Dist: websockets>=10.0
Requires-Dist: yarl>=1,<2
